tests/__init__.py
uniqcharstest9-1.0.dist-info/LICENSE
uniqcharstest9-1.0.dist-info/METADATA
uniqcharstest9-1.0.dist-info/WHEEL
uniqcharstest9-1.0.dist-info/entry_points.txt
uniqcharstest9-1.0.dist-info/top_level.txt
uniqcharstest9-1.0.dist-info/RECORD
